{
	"id": 5,
	"lives": 100,
	"damage": {
		"punch": 3,
		"kick": 6,
		"punchCombo": 13,
		"kickCombo": 15
	},
	"maxEnergy": 100,
	"costs": {
		"punch": 4,
		"kick": 6,
		"punchCombo": 40,
		"kickCombo": 45,
		"jump": 8
	},
	"spriteSheetButton": {
		"spriteSheetIntroImage": "5KarmanSmallIntro.png",
			"spriteDimensions": {
			"width": 3840,
			"height": 164,
			"frameWidth": 212
		},
		"animations": {
			"animation": {
				"name": "introAnimation",
				"startFrame": 0,
				"frames": 12,
				"speed": 0.2,
				"order": "asc"
			}
		},
		"defaultAnimation": "animation"
	},
	"spriteSheetData": {
		"spriteSheetImage": "character5.png",
		"spriteDimensions": {
			"width": 43200,
			"height": 224,
			"frameWidth": 320
		},
		"animations": {
			"damageAnimation": {
				"name": "damageAnimation",
				"startFrame": 0,
				"frames": 8,
				"speed": 0.5,
				"order": "asc"
			},
			"jumpAnimation": {
				"name": "jumpAnimation",
				"startFrame": 8,
				"frames": 10,
				"speed": 0.3,
				"order": "asc"
			},
			"moveLeftAnimation": {
				"name": "moveLeftAnimation",
				"startFrame": 18,
				"frames": 8,
				"speed": 0.5,
				"order": "desc"
			},
			"moveRightAnimation": {
				"name": "moveRightAnimation",
				"startFrame": 18,
				"frames": 8,
				"speed": 0.5,
				"order": "asc"
			},
			"punchAnimation1": {
				"name": "punchAnimation1",
				"startFrame": 26,
				"frames": 10,
				"speed": 0.7,
				"order": "asc"
			},
			"punchAnimation2": {
				"name": "punchAnimation2",
				"startFrame": 36,
				"frames": 3,
				"speed": 0.4,
				"order": "asc"
			},
			"standAnimation": {
				"name": "standAnimation",
				"startFrame": 39,
				"frames": 16,
				"speed": 0.3,
				"order": "asc"
			},
			"jumpKickAnimation": {
				"name": "jumpKickAnimation",
				"startFrame": 55,
				"frames": 12,
				"speed": 0.6,
				"order": "asc"
			},
			"runningAnimation": {
				"name": "runningAnimation",
				"startFrame": 67,
				"frames": 10,
				"speed": 0.35,
				"order": "asc"
			},
			"jumpPunchAnimation": {
				"name": "jumpPunchAnimation",
				"startFrame": 77,
				"frames": 5,
				"speed": 0.2,
				"order": "asc"
			},
			"kickAnimation": {
				"name": "kickAnimation",
				"startFrame": 82,
				"frames": 8,
				"speed": 0.4,
				"order": "desc"
			},
			"punchComboAnimation": {
				"name": "punchComboAnimation",
				"startFrame": 90,
				"frames": 14,
				"speed": 0.6,
				"order": "asc"
			},
			"defendAnimation": {
				"name": "defendAnimation",
				"startFrame": 104,
				"frames": 1,
				"speed": 0.2,
				"order": "asc"
			},
			"kickComboAnimation": {
				"name": "kickComboAnimation",
				"startFrame": 105,
				"frames": 13,
				"speed": 0.5,
				"order": "asc"
			},
			"fatalityAnimation": {
				"name": "fatalityAnimation",
				"startFrame": 118,
				"frames": 7,
				"speed": 0.3,
				"order": "asc"
			},
			"beatenAnimation": {
				"name": "beatenAnimation",
				"startFrame": 125,
				"frames": 10,
				"speed": 0.16,
				"order": "desc"
			}
		},
		"defaultAnimation": "standAnimation"
	},
	"sounds": {
		"kick": 2,
		"punch": 2,
		"comboKick": 1,
		"comboPunch": 1,
		"jump": 1,
		"hit": 3,
		"death": 1
	}
}